markdownfield/__init__.py
markdownfield/apps.py
markdownfield/forms.py
markdownfield/models.py
markdownfield/util.py
markdownfield/validators.py
markdownfield/widgets.py
markdownfield/static/markdownfield/md.css
markdownfield/static/markdownfield/md_admin.css
markdownfield/static/markdownfield/easymde/easymde.min.css
markdownfield/static/markdownfield/easymde/easymde.min.js
markdownfield/static/markdownfield/fontawesome/font-awesome.min.css
markdownfield/static/markdownfield/fontawesome/fonts/FontAwesome.otf
markdownfield/static/markdownfield/fontawesome/fonts/fontawesome-webfont.eot
markdownfield/static/markdownfield/fontawesome/fonts/fontawesome-webfont.svg
markdownfield/static/markdownfield/fontawesome/fonts/fontawesome-webfont.ttf
markdownfield/static/markdownfield/fontawesome/fonts/fontawesome-webfont.woff
markdownfield/static/markdownfield/fontawesome/fonts/fontawesome-webfont.woff2
markdownfield/templates/markdownfield/widget.html
django_markdownfield-0.10.0.dist-info/LICENSE
django_markdownfield-0.10.0.dist-info/WHEEL
django_markdownfield-0.10.0.dist-info/METADATA
django_markdownfield-0.10.0.dist-info/RECORD
